Workbook
Name aa: #REF!
Name aa: #REF!
Name aa: #REF!
Name aa: #REF!
Name aa: #REF!
Name aa: #REF!
Name aa: #REF!
Name aa: #REF!
Name bh: [1]Preliminaries!$J$1
Name bh: [1]Preliminaries!$J$1
Name bh: #REF!
Name Civil4: #REF!
Name Civil4: #REF!
Name Civil4: #REF!
Name Civil4: #REF!
Name Civil4: #REF!
Name Civil4: #REF!
Name Civil4: #REF!
Name Civil4: #REF!
Name d: #REF!
Name d: #REF!
Name d: #REF!
Name d: #REF!
Name d: #REF!
Name d: #REF!
Name d: #REF!
Name date: #REF!
Name date: #REF!
Name date: #REF!
Name date: #REF!
Name date: #REF!
Name date: #REF!
Name date: #REF!
Name date: #REF!
Name daz: #REF!
Name daz: #REF!
Name daz: #REF!
Name daz: #REF!
Name ddd: #REF!
Name ddd: #REF!
Name ddd: #REF!
Name ddd: #REF!
Name for: #REF!
Name for: #REF!
Name for: #REF!
Name for: #REF!
Name for: #REF!
Name job: #REF!
Name job: #REF!
Name job: #REF!
Name job: #REF!
Name job: #REF!
Name No: #REF!
Name No: #REF!
Name No: #REF!
Name No: #REF!
Name No: #REF!
Name qqq: #REF!
Name qqq: #REF!
Name qqq: #REF!

Sheet V1
B6: SUMMARY
V7: Cost | W7: 0 | Y7: Cost | Z7: 0
B8: JOB DESCRIPTION: | K8: 46156 | V8: Markup | W8: 0.1 | Y8: Markup | Z8: 0.1
B9: SITE ADDRESS: | K9: TCS Quote #: 2378 | V9: Charge = | W9: =W7+(W7*W8) -> 0 | Y9: Charge = | Z9: =Z7+(Z7*Z8) -> 0
R10: Cost | S10: (Cost + O/H) + Profit
K11: TOTALS
B13: PART A | F13: Stormwater Drainage (Civil & Hydraulic) | K13: =S13 -> 17860.398 | R13: ='SW Zone Sumry'!F70 -> 13644.307 | S13: =((R13/$R$17)*($R$27-$R$17))+R13 -> 17860.398
R17: =SUM(R13:R15) -> 13644.307 | S17: =SUM(S13:S15) -> 17860.398
T19: Manual Calc
J20: TOTAL ex GST | K20: =SUM(K13:K17) -> 17860.398 | P20: Prelim | Q20: 0.035 | R20: =R17*Q20 -> 477.55075 | S20: of total cost | T20: ='Prelim_OH-Check'!F42 -> 0
P21: O/H | Q21: 0.155 | R21: =R17*Q21 -> 2114.8676 | S21: of total cost | T21: ='Prelim_OH-Check'!F47 -> 0
P23: Sub Total | R23: =SUM(R17:R22) -> 16236.725 | S23: total cost + Prelim + O/H
P26: Gross Profit | Q26: 0.1 | R26: =R23*Q26 -> 1623.6725 | S26: Exl equip & Fixt
P27: Grand Total | R27: =SUM(R23:R26) -> 17860.398
P29: Total Markup | Q29: =SUM(Q20:Q28) -> 0.29
P31: Net Profit Incl Equip | R31: =R26 -> 1623.6725

Sheet Prelim_OH-Check
B1: Project:
B2: Tricore -
B3: Stage 1 Version 1
A4: Item
A7: A | B7: PRELIMINARIES
C8: Unit | D8: REQ | E8: Cost ex GST | F8: Total ex GST
B9: Labour
F10: 0
B11: Contingencies; Wet Weather ?
B13: TRADESMAN_LEADING HAND | C13: Day | D13: 0 | E13: ='Staff Rates'!E17 -> 822.5 | F13: =D13*E13 -> 0
B14: TRADESMAN_PLUMBER_OPERATOR | C14: Day | D14: 0 | E14: 400 | F14: =D14*E14 -> 0
B15: T/A & Apprentice | C15: Day | D15: 0 | E15: 597.62762 | F15: =D15*E15 -> 0
B16: Crew #1 | C16: Day | D16: 0 | E16: 1895.3002 | F16: =D16*E16 -> 0
B17: Crew #2 | C17: Day | D17: 0 | E17: 1511.9133 | F17: 0
B19: Equipment, Hire, Subbies
B21: Dual CabUte | C21: item | D21: 0 | E21: 0 | F21: =D21*E21 -> 0
B22: 10m3_Skip Bin | C22: item | D22: 0 | E22: 0 | F22: =D22*E22 -> 0
B23: TCS Container; Ecl Freight | C23: item | D23: 0 | E23: 0 | F23: =D23*E23 -> 0
B24: Fencing | C24: item | D24: 0 | E24: 0 | F24: =D24*E24 -> 0
C25: item | D25: 0 | E25: 0 | F25: =D25*E25 -> 0
B27: Misc.
B29: Site Admin, Stationary etc - GREENSTAR ADMINS | C29: item | D29: 0 | E29: 1600 | F29: =D29*E29 -> 0
B30: Site PPE | C30: item | D30: 0 | E30: 400 | F30: =D30*E30 -> 0
B31: Site Consumables- Paint, Tapes etc | C31: item | D31: 0 | E31: 180 | F31: =D31*E31 -> 0
B32: Site Management - Bollards, Pickets, Barrier Mesh etc | C32: item | D32: 0 | E32: 400 | F32: =D32*E32 -> 0
B33: Staff Refreshments - ONSITE | C33: item | D33: 0 | E33: 50 | F33: =D33*E33 -> 0
B34: Staff Refreshments - Offsite | C34: item | D34: 0 | E34: 50 | F34: =D34*E34 -> 0
B35: TOOLS - Roll Grover - S&M | C35: item | D35: 0 | E35: 320 | F35: =D35*E35 -> 0
B36: TOOLS - Poly Welder - S&M | C36: item | D36: 0 | E36: 320 | F36: =D36*E36 -> 0
B37: TOOLS - Wacker/Laser/Misc - S&M | C37: item | D37: 0 | E37: 580 | F37: =D37*E37 -> 0
B38: TOOLS - Demo Saw Trolley - PURCHASE | C38: item | D38: 0 | E38: 0 | F38: =D38*E38 -> 0
B39: TOOLS - Consumabls - Blades, etc | C39: item | D39: 0 | E39: 420 | F39: =D39*E39 -> 0
E42: Total TCS Prelims | F42: =SUM(F11:F41) -> 0
A45: A | B45: OverHeads
C46: Unit | D46: REQ | E46: Cost ex GST | F46: Total ex GST
B47: TriCore Overheads - COMPLETE…PER MONTH | C47: item | D47: 0 | E47: 20000 | F47: =D47*E47 -> 0
C48: item | D48: 0 | E48: 0 | F48: 0
C49: item | D49: 0 | E49: 0 | F49: 0
E53: Total TCS O/H | F53: =SUM(F47:F52) -> 0

Sheet SW Zone Sumry
B1: Project:
B2: Tricore -
B3: Stage 1 Version 1
A4: Item
A8: B | B8: Labour
H9: TOTAL Labour
B10: From Proposed Program
H11: =SUM(F13:F19) -> 0
B12: DAY
B13: TRADESMAN_LEADING HAND | C13: Day | E13: ='Staff Rates'!E17 -> 822.5 | F13: =E13*D13 -> 0
B14: CREW - Fire & WAT | C14: Day | E14: ='Staff Rates'!E24 -> 2222.5 | F14: =E14*D14 -> 0
B15: CREW - Drainage | C15: Day | E15: ='Staff Rates'!E24 -> 2222.5 | F15: =E15*D15 -> 0
B16: CREW #3 | C16: Day | E16: ='Staff Rates'!E31 -> 2222.5 | F16: =E16*D16 -> 0
B17: T/A & Apprentice | C17: Day | E17: ='Staff Rates'!E52 -> 612.5 | F17: =E17*D17 -> 0
B18: TRADESMAN.1 | C18: Day | E18: ='Staff Rates'!E45 -> 805 | F18: =E18*D18 -> 0
B19: TRADESMAN.2 | C19: Day | E19: ='Staff Rates'!E45 -> 805 | F19: =E19*D19 -> 0
B21: HOUR
B22: TRADESMAN_LEADING HAND | C22: HR | E22: 0 | F22: =E22*D22 -> 0
B23: TRADESMAN_PLUMBER_OPERATOR | C23: HR | E23: 0 | F23: =E23*D23 -> 0
B24: T/A & Apprentice | C24: HR | E24: 0 | F24: =E24*D24 -> 0
B25: Crew #1 | C25: HR | E25: 0 | F25: =E25*D25 -> 0
B26: Crew #2 | C26: HR | E26: 0 | F26: =E26*D26 -> 0
A28: C | B28: Equipment, Hire, Subbies | H28: TOTAL Equip
B30: Skid Steer Loader_Wheeled | C30: ea | E30: 300 | F30: =E30*D30 -> 0 | H30: =SUM(F30:F39) -> 0
B31: Skid Steer Loader_Wheeled | C31: ea | E31: 300 | F31: =E31*D31 -> 0
B32: 8Ton_Excavator | C32: ea | E32: 300 | F32: =E32*D32 -> 0
B33: 20-24Ton_Excavator | C33: ea | E33: 450 | F33: =E33*D33 -> 0
B34: 14-16Ton_Excavator | C34: ea | E34: 440 | F34: =E34*D34 -> 0
B35: 6-12T_Tipper Truck | C35: ea | E35: 400 | F35: =E35*D35 -> 0
B36: <10T_Articulated Site Tipper | C36: ea | E36: 341 | F36: =E36*D36 -> 0
B37: Trench Roller_Dbl Drum_Remote | C37: ea | E37: 180 | F37: =E37*D37 -> 0
B38: Trench Roller_Dbl Drum_Remote | C38: ea | E38: 180 | F38: =E38*D38 -> 0
B39: <26Ft_Scissor Lift - Diesel | C39: ea | E39: 150 | F39: =E39*D39 -> 0
B40: Compaction Testing | C40: ea | E40: 122 | F40: =E40*D40 -> 0
B41: CCTV | C41: ea | E41: 1680 | F41: =E41*D41 -> 0
B42: Misc Hire/Tooling | C42: ea | E42: 1680 | F42: =E42*D42 -> 0
... B50: Fuel - Diesel_Machinery & Equip/WEEK (Average) | C50: ea | E50: 2500 | F50: =E50*D50 -> 0
E51: **Mini tankers Avg 6,000/Mnth
A53: D | B53: Material
B55: Material; | C55: ea | D55: 1 | E55: =SW_Mataterial!F227 -> 13273.02 | F55: =E55*D55 -> 13273.02
B56: Inground Quarry Products; Complete | C56: ea | D56: 1 | E56: =SW_Mataterial!N268 -> 371.287 | F56: =E56*D56 -> 371.287
B57: MANHOLE Concrete | C57: ea | D57: 1 | E57: =SW_Mataterial!H262 -> 0 | F57: =E57*D57 -> 0
B58: FILTER Install Inc Gravels & Crane | C58: ea | E58: 2120 | F58: =E58*D58 -> 0
B59: Lean mix stab sand etc - ROADS | C59: ea | E59: 1650 | F59: =E59*D59 -> 0
A62: E | B62: Misc
C64: M3 | D64: 0 | E64: 0 | F64: =E64*D64 -> 0
B70: Total Taken forward to Summary | E70: Total | F70: =SUM(F12:F69) -> 13644.307

Sheet SW_Mataterial
B2: SECTION A
B3: STORMWATER DRAINAGE
B4: Description | C4: Qty | D4: Unit | E4: Rate | F4: Total
B6: rcp/frc
B7: PIPE 675MM - RCP_C3 | D7: m | E7: 270 | F7: =C7*E7 -> 0
B8: PIPE 600MM - RCP_C4 | D8: m | E8: =13169/60 -> 219.48333 | F8: =C8*E8 -> 0
B9: PIPE 600MM - RCP_C2 | D9: m | E9: 203 | F9: =C9*E9 -> 0
B10: PIPE 525MM - RCP_C4 | D10: m | E10: 187 | F10: =C10*E10 -> 0
B11: PIPE 525MM - RCP_C3 | D11: m | E11: 140.91 | F11: =C11*E11 -> 0
B12: PIPE 450MM - RCP_C4 | D12: m | E12: =7072.78/53 -> 133.44868 | F12: =C12*E12 -> 0
B13: PIPE 375MM - RCP_C4 | D13: m | E13: =21819.2/243 -> 89.790947 | F13: =C13*E13 -> 0
B14: PIPE 375MM - RCP_C3 | D14: m | E14: 87.11 | F14: =C14*E14 -> 0
B15: PIPE 375MM - RCP_C2 | D15: m | E15: 87.11 | F15: =C15*E15 -> 0
B16: SW_SN8 RIBBED (Blackmax or similar) | D16: m
B17: PIPE Ribbed RRJ 900MM | D17: m
B18: PIPE Ribbed RRJ 825MM | D18: m
B19: PIPE Ribbed RRJ 750MM | D19: m | E19: 232 | F19: =C19*E19 -> 0
B20: PIPE Ribbed RRJ 675MM | D20: m | E20: 232 | F20: =C20*E20 -> 0
B21: PIPE Ribbed RRJ 600MM | D21: m | E21: 120.08 | F21: =C21*E21 -> 0
B22: PIPE Ribbed RRJ 525MM | D22: m | E22: 89 | F22: =C22*E22 -> 0
B23: PIPE Ribbed RRJ 450MM | D23: m | E23: 62.05 | F23: =C23*E23 -> 0
B24: PIPE Ribbed RRJ 375MM | D24: m | E24: 51.55 | F24: =C24*E24 -> 0
B25: PIPE Ribbed RRJ 300MM | C25: 25 | D25: m | E25: 41 | F25: =C25*E25 -> 1025
B26: PIPE Ribbed RRJ 225MM | D26: m | E26: 26 | F26: =C26*E26 -> 0
B27: PIPE Ribbed RRJ 150MM | D27: m | E27: 9.72 | F27: =C27*E27 -> 0
B29: SW_SN8 PVC Pipeline
B30: PIPE DWV SN8 PVC S/WELD 375MM | D30: m | E30: 96.33 | F30: =C30*E30 -> 0
B31: PIPE DWV SN8 PVC S/WELD 300MM | D31: m | E31: 54.33 | F31: =C31*E31 -> 0
B32: PIPE DWV SN4 PVC S/WELD 300MM | D32: m | E32: 49.833333 | F32: =C32*E32 -> 0
B33: PIPE SW H/D PVC S/WELD 300MM | D33: m | E33: 40 | F33: =C33*E33 -> 0
B34: PIPE DWV SN8 PVC S/WELD 225MM | D34: m | E34: =9427.2/237 -> 39.777215 | F34: =C34*E34 -> 0
B35: PIPE DWV SN4 PVC S/WELD 225MM | D35: m | E35: 31 | F35: =C35*E35 -> 0
B36: 50mm PVC Class 12 | D36: m | E36: 18 | F36: =C36*E36 -> 0
B37: PIPE DWV SN8 PVC S/WELD 150MM | D37: m | E37: 14.166667 | F37: =C37*E37 -> 0
B38: PIPE DWV SN4 PVC S/WELD 150MM | D38: m | E38: 11.666667 | F38: =C38*E38 -> 0
B39: PIPE DWV SN4 PVC S/WELD 100MM | C39: 6 | D39: m | E39: 12 | F39: =C39*E39 -> 72
B40: SW Grade Option
B41: 300MM * 45D PVC SW JUNCTION | D41: ea | E41: 159 | F41: =C41*E41 -> 0
B42: 300X225X45D PVC SW JUNCTION | D42: ea | E42: 141.5 | F42: =C42*E42 -> 0
B43: 300MM X 225MM SW Reducer | C43: 2 | D43: ea | E43: 45 | F43: =C43*E43 -> 90
B44: 300MM X 90Deg SW Bend | D44: ea | E44: 49 | F44: =C44*E44 -> 0
B45: 300MM X 45Deg SW Bend | C45: 2 | D45: ea | E45: 44 | F45: =C45*E45 -> 88
B46: 225MM * 45D PVC SW JUNCTION | D46: ea | E46: 51 | F46: =C46*E46 -> 0
B47: 225X150X45D PVC SW JUNCTION | D47: ea | E47: 37 | F47: =C47*E47 -> 0
B48: 225MM X 90Deg SW Bend | D48: ea | E48: 23.5 | F48: =C48*E48 -> 0
B49: 225MM X 45Deg SW Bend | D49: ea | E49: 15 | F49: =C49*E49 -> 0
B50: 150 PVC SW 45Deg Junct | D50: ea | E50: 12.5 | F50: =C50*E50 -> 0
B51: 150MM X 90Deg SW Bend | D51: ea | E51: 5.5 | F51: =C51*E51 -> 0
B52: 150MM X 45Deg SW Bend | D52: ea | E52: 5.5 | F52: =C52*E52 -> 0
B53: DWV Grade Option
B55: 600*225 Ribbed Saddle | D55: ea | E55: 490 | F55: =C55*E55 -> 0
B56: 600*45Deg RIBBED Bend | D56: ea | E56: 650 | F56: =C56*E56 -> 0
B57: 600*450 Ribbed Reducer | D57: ea | E57: 1100 | F57: =C57*E57 -> 0
B58: 450*375 Ribbed*PVC Reducer | D58: ea | E58: 460 | F58: =C58*E58 -> 0
B59: 450 45 Deg ribbed Bend | D59: ea | E59: 580 | F59: =C59*E59 -> 0
B60: 450 * 225 Ribbed Saddle | D60: ea | E60: 320 | F60: =C60*E60 -> 0
B61: 375mm X 45Deg Junction | D61: ea | E61: 420 | F61: =C61*E61 -> 0
B62: 375X300X45D PVC JUNCTION | D62: ea | E62: 562.39 | F62: =C62*E62 -> 0
B63: 375X225X45D PVC JUNCTION | D63: ea | E63: 563.39 | F63: =C63*E63 -> 0
B64: 375MM X 300MM Reducer | D64: ea | E64: 380 | F64: =C64*E64 -> 0
B65: 375MM X 225MM Reducer | D65: ea | E65: 360 | F65: =C65*E65 -> 0
B66: 375MM X 90Deg Bend | D66: ea | E66: 540 | F66: =C66*E66 -> 0
... B72: 300MM X 45Deg Bend | D72: ea | E72: 190 | F72: =C72*E72 -> 0
B73: 300MM X 150 Junction
B74: 225MM * 45D PVC JUNCTION | D74: ea | E74: 85.25 | F74: =C74*E74 -> 0
B75: 225X150X45D PVC JUNCTION | D75: ea | E75: 210 | F75: =C75*E75 -> 0
B76: 225MM X 90Deg Bend | D76: ea | E76: 62 | F76: =C76*E76 -> 0
B77: 225MM X 45Deg Bend | D77: ea | E77: 61 | F77: =C77*E77 -> 0
B78: 225MM X 150MM Reducer | D78: ea | E78: 120 | F78: =C78*E78 -> 0
B79: 150MM X 100MM Reducer | D79: ea | E79: 85 | F79: =C79*E79 -> 0
B80: 150 PVC DWV 45Deg Junct | D80: ea | E80: 18 | F80: =C80*E80 -> 0
B81: 150MM X 90Deg Bend | D81: ea | E81: 16 | F81: =C81*E81 -> 0
B82: 150MM X 45Deg Bend | D82: ea | E82: 12 | F82: =C82*E82 -> 0
B83: 150X100X45D PVC JUNCTION | D83: ea | E83: 16 | F83: =C83*E83 -> 0
B84: 100 X 45D PVC JUNCTION | C84: 1 | D84: ea | E84: 14 | F84: =C84*E84 -> 14
B85: 100MM X 90Deg Bend | D85: ea | E85: 12 | F85: =C85*E85 -> 0
B86: 100MM X 45Deg Bend | D86: ea | E86: 12 | F86: =C86*E86 -> 0
B87: 150mm PVC 10mm nut hanging clip | D87: ea | E87: 1.9 | F87: =C87*E87 -> 0
B88: 10mm Zinc Threaded Rod | D88: m | E88: 2 | F88: =C88*E88 -> 0
B89: Glue - Blue - 4Ltr | D89: ea | E89: 26.4 | F89: =C89*E89 -> 0
B90: Primer - Red - 4Ltr | D90: ea | E90: 23 | F90: =C90*E90 -> 0
B91: 600*600 pits | D91: ea | E91: 990 | F91: =C91*E91 -> 0
B93: SW_Gully/Pit
B94: Concrete/GRC - Class D - 450SQ Pit w/base - 450H | C94: 2 | D94: ea | E94: 139 | F94: =C94*E94 -> 278
B95: Concrete/GRC - Class D - 450SQ Pit w/base - 600H | D95: ea | E95: 190 | F95: =C95*E95 -> 0
B96: Concrete/GRC - Class D - 450SQ Riser - 150H | D96: ea | E96: 102 | F96: =C96*E96 -> 0
B97: Concrete/GRC - Class D - 450SQ Riser - 300H | D97: ea | E97: 124 | F97: =C97*E97 -> 0
B98: Concrete/GRC - Class D - 450SQ Riser - 450H | D98: ea | E98: 135 | F98: =C98*E98 -> 0
B99: Concrete/GRC - Class D - 600SQ Pit w/base - 450H | D99: ea | F99: =C99*E99 -> 0
B100: Concrete/GRC - Class D - 600SQ Pit w/base - 600H | D100: ea | E100: 168 | F100: =C100*E100 -> 0
B101: Concrete/GRC - Class D - 900SQ Pit w/base - 450H | D101: ea | F101: =C101*E101 -> 0
B102: Concrete/GRC - Class D - 900SQ Pit w/base - 600H | D102: ea | E102: 355 | F102: =C102*E102 -> 0
B103: Concrete/GRC - Class D - 900SQ Pit w/base - 900H | C103: 1 | D103: ea | E103: 370 | F103: =C103*E103 -> 370
B104: Concrete/GRC - Class D - 600SQ Riser - 150H | D104: ea | E104: 109 | F104: =C104*E104 -> 0
B105: Concrete/GRC - Class D - 600SQ Riser - 300H | D105: ea | E105: 138 | F105: =C105*E105 -> 0
B106: Concrete/GRC - Class D - 600SQ Riser - 600H | D106: ea | E106: 201.25 | F106: =C106*E106 -> 0
B107: Concrete/GRC - Class D - 600SQ Riser - 900H | D107: ea
B108: Concrete/GRC - Class D - 900SQ Pit w/base - 900H | D108: ea | E108: 370 | F108: =C108*E108 -> 0
B109: Concrete/GRC - Class D - 900SQ Riser - 150H | D109: ea | E109: 145 | F109: =C109*E109 -> 0
B110: Concrete/GRC - Class D - 900SQ Riser - 300H | D110: ea | E110: 190 | F110: =C110*E110 -> 0
...

Sheet SW_Pit Takeoff
C1: 44918
G2: Total Qty
C3: 600 Grte/frm Height | E3: 0.055
C4: 600*900 Grte/frm Height | E4: 0.08
C5: 1.2*1.2 Grte/frm Height | E5: 0.14
C6: 1200*9*6 ASPRO Height | E6: 0.175
C7: 600 infl Height | E7: 0.055
C8: 600 V Grate Height | E8: 0.15
C9: 600 Pit Base Height | E9: 0.6
C10: 600 Pit Riser Height | E10: 0.15
C11: 600 Pit Riser Height | E11: 0.3
C12: 600 Pit Riser Height | E12: 0.6
C13: 600 Pit Riser Height | E13: 0.9
C14: 900*900 Pit Base Height | E14: 0.9
... C18: 600*900 Pit Riser Height | E18: 0.9
C19: 1050 Chmbr Base Height | E19: 1.2 | F19: 1200
C20: 1050 Chmbr Riser Height | E20: 0.15
C21: 1050 Chmbr Riser Height | E21: 0.3
C22: 1050 Chmbr Riser Height | E22: 0.6
C23: 1050 Chmbr Riser Height | E23: 0.9
C24: 1050 Chmbr Riser Height | E24: 1.2
D25: 1200*1200*200 | E25: 0.2 | AG25: 0.2for1.2
O26: Manual calc | AD26: V3 | AG26: Manual calc | AV26: V3 | AX26: Manual calc
C27: Pit Count | D27: PIT No. | E27: Grate RL | F27: Type | G27: Grate Size | H27: Chamber | I27: Outlet IL | J27: Depth | M27: Riser Height Req. w/ base | O27: 0.15 Riser | P27: 0.3 Riser | Q27: 0.6 Riser | R27: 0.9 Riser | T27: Pit riser difference | V27: Pit Count | W27: PIT No. | X27: Grate RL | Y27: Type | Z27: Grate Size | AA27: Chamber | AB27: Outlet IL | AC27: Depth | AE27: Riser Height Req. w/base | AG27: 0.15 Riser | AH27: 0.3 Riser | AI27: 0.6 Riser | AJ27: 0.9 Riser | AK27: Pit riser difference | AM27: Pit Count | AN27: PIT No. | AO27: Grate RL | AP27: Type | AQ27: Grate Size | AR27: Chamber | AS27: Outlet IL | AT27: Depth | AW27: Riser Height Req. w/ base | AX27: 0.15 Riser | AY27: 0.3 Riser | AZ27: 0.6 Riser | BA27: 0.9 Riser | BB27: Pit riser difference
C28: 1 | J28: =E28-I28 -> 0 | M28: =J28-0.45-0.05 -> -0.5 | T28: =M28-(O28*$E$10)-(P28*$E$11)-(Q28*$E$12)-(R28*$E$13) -> -0.5 | V28: 21 | AC28: 0.986 | AD28: 1 | AE28: =AC28-$E$3-0.3 -> 0.631 | AI28: 1 | AK28: =AE28-(AG28*$E$25)-(AH28*$E$11)-(AI28*$E$12)-(AJ28*$E$13) -> 0.031 | AM28: 40 | AN28: 46 | AV28: =AT28-$E$9-$E$8 -> -0.75 | AW28: =AT28-$E$5-$E$19 -> -1.34 | BB28: =AW28-(AX28*$E$25)-(AY28*$E$11)-(AZ28*$E$12)-(BA28*$E$13) -> -1.34
C29: 2 | J29: =E29-I29 -> 0 | M29: =J29-$E$9-$E$3 -> -0.655 | T29: =M29-(O29*$E$10)-(P29*$E$11)-(Q29*$E$12)-(R29*$E$13) -> -0.655 | V29: 22 | AC29: 0.949 | AD29: =Y29-AC29 -> -0.949 | AE29: =AC29-$E$3-0.3 -> 0.594 | AI29: 1 | AK29: =AE29-(AG29*$E$10)-(AH29*$E$11)-(AI29*$E$12)-(AJ29*$E$13) -> -0.006 | AM29: 42 | AN29: 47 | AV29: =AT29-$E$9-$E$8 -> -0.75 | AW29: =AT29-$E$5-$E$19 -> -1.34 | BB29: =AW29-(AX29*$E$10)-(AY29*$E$11)-(AZ29*$E$12)-(BA29*$E$13) -> -1.34
C30: 3 | J30: =E30-I30 -> 0 | M30: =J30-$E$3-$E$9 -> -0.655 | T30: =M30-(O30*$E$10)-(P30*$E$11)-(Q30*$E$12)-(R30*$E$13) -> -0.655 | V30: 23 | AC30: =X30-AB30 -> 0 | AE30: =AC30-$E$4-$E$14 -> -0.98 | AK30: =AE30-(AG30*$E$10)-(AH30*$E$11)-(AI30*$E$12)-(AJ30*$E$13) -> -0.98 | AM30: 43 | AV30: =AT30-$E$9-$E$8 -> -0.75 | AW30: =AT30-$E$4-$E$14 -> -0.98 | BB30: =AW30-(AX30*$E$10)-(AY30*$E$11)-(AZ30*$E$12)-(BA30*$E$13) -> -0.98
C31: 4 | J31: =E31-I31 -> 0 | M31: =J31-$E$6-$E$23-$E$4 -> -1.155 | T31: =M31-(O31*$E$10)-(P31*$E$11)-(Q31*$E$12)-(R31*$E$13) -> -1.155 | V31: 24 | AD31: 2.1 | AE31: =AC31-$E$4-$E$14 -> -0.98 | AK31: =AE31-(AG31*$E$10)-(AH31*$E$11)-(AI31*$E$12)-(AJ31*$E$13) -> -0.98 | AM31: 44 | AV31: =AT31-$E$9-$E$8 -> -0.75 | AW31: =AT31-$E$4-$E$14 -> -0.98 | BB31: =AW31-(AX31*$E$10)-(AY31*$E$11)-(AZ31*$E$12)-(BA31*$E$13) -> -0.98
C32: 5 | J32: =E32-I32 -> 0 | M32: =J32-$E$3-$E$9 -> -0.655 | T32: =M32-(O32*$E$10)-(P32*$E$11)-(Q32*$E$12)-(R32*$E$13) -> -0.655 | V32: 25 | AD32: 0.86 | AE32: =AC32-$E$4-$E$14 -> -0.98 | AK32: =AE32-(AG32*$E$25)-(AH32*$E$11)-(AI32*$E$12)-(AJ32*$E$13) -> -0.98 | AM32: 45 | AV32: =AT32-$E$9-$E$8 -> -0.75
C33: 6 | J33: =E33-I33 -> 0 | M33: =J33-$E$3-$E$9 -> -0.655 | T33: =M33-(O33*$E$10)-(P33*$E$11)-(Q33*$E$12)-(R33*$E$13) -> -0.655 | V33: 26 | AD33: 2.26 | AE33: =AC33-$E$4-$E$14 -> -0.98 | AK33: =AE33-(AG33*$E$25)-(AH33*$E$11)-(AI33*$E$12)-(AJ33*$E$13) -> -0.98 | AM33: 46 | AV33: =AT33-$E$9-$E$8 -> -0.75
C34: 7 | J34: =E34-I34 -> 0 | M34: =J34-$E$4-$E$14 -> -0.98 | T34: =M34-(O34*$E$10)-(P34*$E$11)-(Q34*$E$12)-(R34*$E$13) -> -0.98 | V34: 27 | AD34: 1.96 | AE34: =AC34-$E$4-$E$14 -> -0.98 | AK34: =AE34-(AG34*$E$25)-(AH34*$E$11)-(AI34*$E$12)-(AJ34*$E$13) -> -0.98 | AM34: 47 | AV34: =AT34-$E$9-$E$8 -> -0.75
C35: 8 | J35: =E35-I35 -> 0 | M35: =J35-$E$3-$E$9 -> -0.655 | T35: =M35-(O35*$E$10)-(P35*$E$11)-(Q35*$E$12)-(R35*$E$13) -> -0.655 | V35: 28 | AD35: 2.1 | AE35: =AC35-$E$4-$E$14 -> -0.98 | AK35: =AE35-(AG35*$E$25)-(AH35*$E$11)-(AI35*$E$12)-(AJ35*$E$13) -> -0.98 | AM35: 48 | AV35: =AT35-$E$9-$E$8 -> -0.75
C36: 9 | J36: =E36-I36 -> 0 | M36: =J36-$E$6-$E$23-$E$4 -> -1.155 | T36: =M36-(O36*$E$10)-(P36*$E$11)-(Q36*$E$12)-(R36*$E$13) -> -1.155 | AD36: 2.1 | AE36: =AC36-$E$4-$E$14 -> -0.98 | AK36: =AE36-(AG36*$E$25)-(AH36*$E$11)-(AI36*$E$12)-(AJ36*$E$13) -> -0.98
C37: 10 | J37: =E37-I37 -> 0 | M37: =J37-$E$3-$E$9 -> -0.655 | T37: =M37-(O37*$E$10)-(P37*$E$11)-(Q37*$E$12)-(R37*$E$13) -> -0.655 | AD37: 2.1 | AE37: =AC37-$E$4-$E$14 -> -0.98 | AK37: =AE37-(AG37*$E$25)-(AH37*$E$11)-(AI37*$E$12)-(AJ37*$E$13) -> -0.98
C38: 11 | J38: =E38-I38 -> 0 | M38: =J38-$E$3-$E$9 -> -0.655 | T38: =M38-(O38*$E$10)-(P38*$E$11)-(Q38*$E$12)-(R38*$E$13) -> -0.655 | AD38: 2.1 | AE38: =AC38-$E$4-$E$14 -> -0.98 | AK38: =AE38-(AG38*$E$25)-(AH38*$E$11)-(AI38*$E$12)-(AJ38*$E$13) -> -0.98
C39: 12 | J39: =E39-I39 -> 0 | M39: =J39-0.45-$E$3 -> -0.505 | T39: =M39-(O39*$E$10)-(P39*$E$11)-(Q39*$E$12)-(R39*$E$13) -> -0.505 | AD39: 2.1 | AE39: =AC39-$E$4-$E$14 -> -0.98 | AK39: =AE39-(AG39*$E$25)-(AH39*$E$11)-(AI39*$E$12)-(AJ39*$E$13) -> -0.98
C40: 13 | J40: 0.767 | M40: =J40-0.45-$E$3 -> 0.262 | T40: =M40-(O40*$E$10)-(P40*$E$11)-(Q40*$E$12)-(R40*$E$13) -> 0.262 | AD40: 2.1 | AE40: =AC40-$E$4-$E$14 -> -0.98 | AK40: =AE40-(AG40*$E$10)-(AH40*$E$11)-(AI40*$E$12)-(AJ40*$E$13) -> -0.98
C41: 14 | J41: 0.882 | M41: =J41-0.45-$E$3 -> 0.377 | T41: =M41-(O41*$E$10)-(P41*$E$11)-(Q41*$E$12)-(R41*$E$13) -> 0.377 | AD41: 2.1 | AE41: =AC41-$E$4-$E$14 -> -0.98 | AK41: =AE41-(AG41*$E$25)-(AH41*$E$11)-(AI41*$E$12)-(AJ41*$E$13) -> -0.98
C42: 15 | J42: 1.291 | M42: =J42-$E$3-$E$9 -> 0.636 | T42: =M42-(O42*$E$10)-(P42*$E$11)-(Q42*$E$12)-(R42*$E$13) -> 0.636 | AD42: 2.1 | AE42: =AC42-$E$4-$E$14 -> -0.98 | AK42: =AE42-(AG42*$E$10)-(AH42*$E$11)-(AI42*$E$12)-(AJ42*$E$13) -> -0.98
C43: 16 | J43: 0.969 | M43: =J43-0.45-$E$3 -> 0.464 | T43: =M43-(O43*$E$10)-(P43*$E$11)-(Q43*$E$12)-(R43*$E$13) -> 0.464 | AD43: 2.1 | AE43: =AC43-$E$4-$E$14 -> -0.98 | AK43: =AE43-(AG43*$E$10)-(AH43*$E$11)-(AI43*$E$12)-(AJ43*$E$13) -> -0.98
C44: 17 | J44: =E44-I44 -> 0 | M44: =J44-$E$4-$E$14 -> -0.98 | T44: =M44-(O44*$E$10)-(P44*$E$11)-(Q44*$E$12)-(R44*$E$13) -> -0.98 | AD44: 2.1 | AE44: =AC44-$E$4-$E$14 -> -0.98 | AK44: =AE44-(AG44*$E$10)-(AH44*$E$11)-(AI44*$E$12)-(AJ44*$E$13) -> -0.98
C45: 18 | J45: =E45-I45 -> 0 | M45: =J45-$E$4-$E$14 -> -0.98 | T45: =M45-(O45*$E$10)-(P45*$E$11)-(Q45*$E$12)-(R45*$E$13) -> -0.98 | AD45: 2.1 | AE45: =AC45-$E$4-$E$14 -> -0.98 | AK45: =AE45-(AG45*$E$10)-(AH45*$E$11)-(AI45*$E$12)-(AJ45*$E$13) -> -0.98
C46: 19 | J46: 2.51 | M46: =J46-$E$4-$E$14 -> 1.53 | T46: =M46-(O46*$E$10)-(P46*$E$11)-(Q46*$E$12)-(R46*$E$13) -> 1.53 | AD46: 2.1 | AE46: =AC46-$E$4-$E$14 -> -0.98 | AK46: =AE46-(AG46*$E$10)-(AH46*$E$11)-(AI46*$E$12)-(AJ46*$E$13) -> -0.98
C47: 20 | J47: 0.615 | M47: =J47-$E$3-$E$9 -> -0.04 | T47: =M47-(O47*$E$10)-(P47*$E$11)-(Q47*$E$12)-(R47*$E$13) -> -0.04 | AD47: 2.1 | AE47: =AC47-0.045-$E$14 -> -0.945 | AK47: =AE47-(AG47*$E$10)-(AH47*$E$11)-(AI47*$E$12)-(AJ47*$E$13) -> -0.945
M50: Pit Bases | O50: 0.15 Riser | P50: 0.3 Riser | Q50: 0.6 Riser | R50: 0.9 Riser | AE50: Pits | AG50: 0.15 Riser | AH50: 0.3 Riser | AI50: 0.6 Riser | AJ50: 0.9 Riser | AW50: Pits | AX50: 0.15 Riser | AY50: 0.3 Riser | AZ50: 0.6 Riser | BA50: 0.9 Riser
J51: 300x300 ploy
J52: 450x450 poly | AB52: 900High | AC52: 900*600 | AG52: =SUM(AG47,AG31,AG40) -> 0 | AH52: =SUM(AH47,AH31,AH40) -> 0 | AI52: =SUM(AI47,AI31,AI40) -> 0 | AJ52: =SUM(AJ47,AJ31,AJ40) -> 0 | AT52: 900High | AU52: 900*600
J53: 450*450 | N53: 450High | AC53: 1050 | AG53: =SUM(AG41:AG44,AG32:AG37,AG28) -> 0 | AH53: =SUM(AH41:AH44,AH32:AH37,AH28) -> 0 | AI53: =SUM(AI41:AI44,AI32:AI37,AI28) -> 1 | AJ53: =SUM(AJ41:AJ44,AJ32:AJ37,AJ28) -> 0 | AU53: 1050 | AW53: =COUNTA(AR28:AR29) -> 0 | AX53: =SUM(AX28:AX29) -> 0 | AY53: =SUM(AY28:AY29) -> 0 | AZ53: =SUM(AZ28:AZ29) -> 0 | BA53: =SUM(BA28:BA29) -> 0
J54: 600*600 | N54: 600High | AC54: 1200 | AG54: =COUNTA(AG38:AG39,AG45) -> 0 | AH54: =COUNTA(AH38:AH39,AH45) -> 0 | AI54: =COUNTA(AI38:AI39,AI45) -> 0 | AJ54: =COUNTA(AJ38:AJ39,AJ45) -> 0 | AU54: 1200
J55: 900*900 | N55: 900High
J56: 1050 dia | N56: 900 high
J57: 1200x1200 | N57: 1200 High
I58: 1st Order | J58: 1500x1500 | N58: 1200 High | AB58: 1st Order | AC58: 600*600 | AT58: 1st Order | AU58: 600*600
J59: 2100 | N59: 900 high | AC59: 900*600 | AU59: 900*600
J60: 2100 | N60: 600 High | AC60: 1050 | AU60: 1050
J61: 2100 | N61: 300 High
O64: 0.2R 1.2*1.2
M66: Pit Bases | O66: 0.15 Riser | P66: 0.3 Riser | Q66: 0.6 Riser | R66: 0.9 Riser
I67: TOTAL | J67: 900*600 | N67: 600High
J68: 900*600 | N68: 900High | O68: 0 | P68: 0 | Q68: 0 | R68: 0
J69: 1050Dia | O69: 0 | P69: 0 | Q69: =Q56+AI53+AZ53 -> 1 | R69: =R56+AJ53+BA53 -> 0
J70: 1200Dia | O70: 0 | P70: 0 | Q70: =Q57+AI54+AZ54 -> 0 | R70: =R57+AJ54+BA54 -> 0
J73: 1200 Pit | K73: In lieu of 1050&1200Ch | N73: 1200High | Q73: =Q69+Q70 -> 1 | R73: =R69+R70 -> 0
M77: Grates/Covers
I78: TOTAL | J78: 450x450 | L78: =COUNTA(G28,G39,G40,G41,G43) -> 0 | M78: heel safe grate cover | O78: CL D, Hinged, Galv, Bolt Down.
J79: 600x600 | L79: =COUNTA(G30,G32,G37,G38) -> 0 | M79: heel safe grate cover | O79: CL D, Hinged, Galv, Bolt Down.
J80: 600X600 | L80: =COUNTA(G29,G31,G33,G35,G42,G47) -> 0 | M80: Grate &Frame | O80: CL D, Cast Iron
J81: 600x900 | M81: heel safe grate cover | O81: CL D, Hinged, Galv, Bolt Down.
J82: 600x900 | L82: =COUNTA(G31) -> 0 | M82: Grate &Frame | O82: CL D, Hinged, Galv, Bolt Down.
J83: 900X900 | L83: =COUNTA(G46) -> 0 | M83: Grate &Frame | O83: CL D, Hinged, Galv, Bolt Down.
J84: 900X600 | L84: =COUNTA(G36) -> 0 | M84: 900x600 cast Iron lid and concret around | O84: CL D, Cast Iron
J85: 1050*6*9 | L85: =COUNTA(H31,H36) -> 0 | M85: Aspro | O85: 150Thick, 900*600 Opening
J86: 1200x900 | M86: Grate & Frame | O86: CL D, Hinged, Galv, Bolt Down.
J87: 1200*1200 overflow pit | M87: Grate & Frame | O87: CL D, Hinged, Galv, Bolt Down.
J88: 900x900 Class D hinged grate and frame with a concrete surroun
M89: 2.4m lintel | O89: 3.6m SAG centre inlet, Kerb in line
M90: Headwall (250mm pipe )
M91: headwall(600mm pipe )
M92: Twin Pipe Headwall ( 300mm /225mm pipe )
M96: Head Wall | O96: Precast - 450RCP Inlet
M99: Pit Bases | O99: 0.15 Riser | P99: 0.3 Riser | Q99: 0.6 Riser | R99: 0.9 Riser
I100: 1st PIT Order | J100: 600*600 | N100: 600High
J101: 900*900 | N101: 900High
J102: 900*600 | N102: 600High
J103: 900*600 | N103: 900High
J104: 1050 | N104: 0High
M106: Grates/Covers
I107: 1St GRATE Order | J107: 600*600 | M107: Grate & Frame | O107: CL D, Galv, Bolt Down.
J108: 600*600 | M108: Grate & Frame | O108: CL B, Galv, Bolt Down.
J109: 600*600 | M109: Cover & Frm - INFILL | O109: CL B, Galv, Bolt Down.
J110: 600*600 | M110: V-Grate w/conc surround | O110: CL B, Galv
J111: 900*600 | M111: Grate & Frame | O111: CL D, Galv, Bolt Down.
J112: 900*600 | M112: Grate & Frame | O112: CL D, Galv, Bolt Down - HEEL GUARD
J113: 900*900 | M113: Grate & Frame | O113: CL D, Galv, Bolt Down - HEEL GUARD
J114: 1050*6*9 | M114: Aspro | O114: 150Thick, 900*600 Opening
M117: Grates/Covers
I118: 2nd GRATE Order | J118: 600*600 | M118: Grate & Frame | O118: CL D, Galv, Bolt Down.
J119: 600*600 | M119: Grate & Frame | O119: CL B, Galv, Bolt Down.
J120: 600*600 | M120: Cover & Frm - INFILL | O120: CL B, Galv, Bolt Down.
J121: 600*600 | M121: V-Grate w/conc surround | O121: CL B, Galv
...

Sheet SW_insitu Takeoff
B2: PIT/MANHOLE TAKEOFF
A3: DESCRIPTION | B3: Design Depth | C3: Grate/Finish | D3: Aspro | E3: Total Chamber Height | F3: Chamber Concrete volume/m3 | G3: Base Concrete volume/m3 | H3: Total Concrete volume/m3 | J3: Dia | K3: Area of circle
H4: =F4+G4 -> 0 | J4: 2.1 | K4: =PI()*(J4/2)^2 -> 3.4636059 | L4: m2
J5: 2.6 | K5: =PI()*(J5/2)^2 -> 5.3092916 | L5: m2
K6: =PI()*(J6/2)^2 -> 0 | L6: m2
K7: =PI()*(J7/2)^2 -> 0 | L7: m2
J10: 32 | K10: MPA | L10: 290 | M10: $/m3
L24: =H24-G24 -> 0
H27: =SUM(H4:H16) -> 0 | I27: m3 | J27: =H27*L10 -> 0

Sheet Program
A1: Project Program | D1: MONTH 1 | AF1: MONTH 2 | BH1: MONTH 3 | CJ1: MONTH 4 | DL1: MONTH 5
D2: Week 1 / SEPT | K2: Week 2 / SEPT | R2: Week 3 / SEPT | Y2: Week 4 / SEPT | AF2: Week 5 / OCT | AM2: Week 6 / OCT | AT2: Week 7 / OCT | BA2: Week 8 / OCT | BH2: Week 9 / NOV | BO2: Week 10 / NOV | BV2: Week 11 / NOV | CC2: Week 12 / NOV | CJ2: Week 13 / NOV-DEC | CQ2: Week 14 / DEC | CX2: Week 15 / DEC | DE2: Week 16 / NOV | DL2: Week 17 / NOV-DEC
D3: M | E3: Tu | F3: W | G3: Th | H3: F | I3: Sa | J3: Su | K3: M | L3: Tu | M3: W | N3: Th | O3: F | P3: Sa | Q3: Su | R3: M | S3: Tu | T3: W | U3: Th | V3: F | W3: Sa | X3: Su | Y3: M | Z3: Tu | AA3: W | AB3: Th | AC3: F | AD3: Sa | AE3: Su | AF3: M | AG3: Tu | AH3: W | AI3: Th | AJ3: F | AK3: Sa | AL3: Su | AM3: M | AN3: Tu | AO3: W | AP3: Th | AQ3: F | AR3: Sa | AS3: Su | AT3: M | AU3: Tu | AV3: W | AW3: Th | AX3: F | AY3: Sa | AZ3: Su | BA3: M | BB3: Tu | BC3: W | BD3: Th | BE3: F | BF3: Sa | BG3: Su | BH3: M | BI3: Tu | BJ3: W | BK3: Th | BL3: F | BM3: Sa | BN3: Su | BO3: M | BP3: Tu | BQ3: W | BR3: Th | BS3: F | BT3: Sa | BU3: Su | BV3: M | BW3: Tu | BX3: W | BY3: Th | BZ3: F | CA3: Sa | CB3: Su | CC3: M | CD3: Tu | CE3: W | CF3: Th | CG3: F | CH3: Sa | CI3: Su | CJ3: M | CK3: Tu | CL3: W | CM3: Th | CN3: F | CO3: Sa | CP3: Su | CQ3: M | CR3: Tu | CS3: W | CT3: Th | CU3: F | CV3: Sa | CW3: Su | CX3: M | CY3: Tu | CZ3: W | DA3: Th | DB3: F | DC3: Sa | DD3: Su | DE3: M | DF3: Tu | DG3: W | DH3: Th | DI3: F | DJ3: Sa | DK3: Su | DL3: M | DM3: Tu | DN3: W | DO3: Th | DP3: F | DQ3: Sa | DR3: Su
D4: 4 | E4: 5 | F4: 6 | G4: 7 | H4: 8 | I4: 9 | J4: 10 | K4: 11 | L4: 12 | M4: 13 | N4: 14 | O4: 15 | P4: 16 | Q4: 17 | R4: 18 | S4: 19 | T4: 20 | U4: 21 | V4: 22 | W4: 23 | X4: 24 | Y4: 25 | Z4: 26 | AA4: 27 | AB4: 28 | AC4: 29 | AD4: 30 | AE4: 1 | AF4: 2 | AG4: 3 | AH4: 4 | AI4: 5 | AJ4: 6 | AK4: 7 | AL4: 8 | AM4: 9 | AN4: 10 | AO4: 11 | AP4: 12 | AQ4: 13 | AR4: 14 | AS4: 15 | AT4: 16 | AU4: 17 | AV4: 18 | AW4: 19 | AX4: 20 | AY4: 21 | AZ4: 22 | BA4: 23 | BB4: 24 | BC4: 25 | BD4: 26 | BE4: 27 | BF4: 28 | BG4: 29 | BH4: 30 | BI4: 31 | BJ4: 1 | BK4: 2 | BL4: 3 | BM4: 4 | BN4: 5 | BO4: 6 | BP4: 7 | BQ4: 8 | BR4: 9 | BS4: 10 | BT4: 11 | BU4: 12 | BV4: 13 | BW4: 14 | BX4: 15 | BY4: 16 | BZ4: 17 | CA4: 18 | CB4: 19 | CC4: 20 | CD4: 21 | CE4: 22 | CF4: 23 | CG4: 24 | CH4: 25 | CI4: 26 | CJ4: 27 | CK4: 28 | CL4: 29 | CM4: 30 | CN4: 1 | CO4: 2 | CP4: 3 | CQ4: 4 | CR4: 5 | CS4: 6 | CT4: 7 | CU4: 8 | CV4: 9 | CW4: 10 | CX4: 11 | CY4: 12 | CZ4: 13 | DA4: 14 | DB4: 15 | DC4: 16 | DD4: 17 | DE4: 18 | DF4: 19 | DG4: 20 | DH4: 21 | DI4: 22 | DJ4: 23 | DK4: 24 | DL4: 25 | DM4: 26 | DN4: 27 | DO4: 28 | DP4: 29 | DQ4: 30 | DR4: 31
B5: Contract Execution, Contract Insurances and Exchanges
B6: Design Assessment, Coordination, Shop Drawings etc_For Construction
B7: Site Inductions
A8: Mobilsation | B8: BUILDERS Proj DURATION:
B9: TEMPS
B10: Materials Store, Area establishment, signage and controls
A12: Road 5 | B12: 670LM - 2 Tees - Serving 20 Lots
A14: Road 6 | B14: 100LM - Serving 5 Lots
A16: Road 7 | B16: 500LM - Serving 19 Lots
A18: Live Connection #1
A20: Live Connection #2
A22: Contract Completion
B24: Commissioning
B25: As-Built
B26: O+M Manuals
B27: Pratical Completion
B28: Site Demobilisation
A30: Staff Count
B33: TRADESMAN_LEADING HAND | DR33: 0
B34: CREW - Fire & WAT
B35: CREW - Drainage
B36: CREW #3
B37: T/A & Apprentice
B38: TRADESMAN.1
B39: TRADESMAN.2
B41: Qty Staff On Site | D41: =D33+(D34*3)+(D35*3)+(D36*3)+D37+D38+D39 -> 0 | E41: =E33+(E34*3)+(E35*3)+(E36*3)+E37+E38+E39 -> 0 | F41: =F33+(F34*3)+(F35*3)+(F36*3)+F37+F38+F39 -> 0 | G41: =G33+(G34*3)+(G35*3)+(G36*3)+G37+G38+G39 -> 0 | H41: =H33+(H34*3)+(H35*3)+(H36*3)+H37+H38+H39 -> 0 | I41: =I33+(I34*3)+(I35*3)+(I36*3)+I37+I38+I39 -> 0 | J41: =J33+(J34*3)+(J35*3)+(J36*3)+J37+J38+J39 -> 0 | K41: =K33+(K34*3)+(K35*3)+(K36*3)+K37+K38+K39 -> 0 | ... DR41: =DR33+(DR34*3)+(DR35*3)+(DR36*3)+DR37+DR38+DR39 -> 0
B43: Total Days - LEAD HAND - PRELIM | C43: =SUM(D33:CV33) -> 0
B44: Hyd allow **
B45: Civil SW allow **
B47: Total Days - CREW - FIRE_WAT | C47: =SUM(D34:CV34) -> 0
B48: Total - CREW "Drainage" | C48: =SUM(D35:CV35) -> 0
B49: HYD - CREW "Drainage"
B50: Civil SW - CREW "Drainage"
B51: Total Days CREW 3
B52: Total Days - TA | C52: =SUM(D37:CV37) -> 0
B53: Total Days - Tradesman.1 | C53: =SUM(D38:CV38) -> 0
B54: Hyd - Tradesman.1
B55: Civil SW - Tradesman.1
B56: Total Days - Tradesman.2
B57: Hyd - Tradesman.2
B58: Civil SW - Tradesman.2

Sheet Staff Rates
B1: Project:
B2: Tricore -
B3: Stage 1 Version 1
A4: Item
B6: BASED ON:
B7: 6 - Day Week, 10Hr Day | F7: 2023 Staff Cost increase | G7: Project total cost | H7: Difference
B8: Working Days/Month | C8: 24 | F8: Current
B9: No-Work Days/Month | C9: 4 | F9: 0.025 | G9: =G8+(G8*F9) -> 0 | H9: =G9-G8 -> 0
B10: Avrg Hours / Day | C10: 8.75 | F10: 0.05 | G10: =G9+(G9*F10) -> 0 | H10: =G10-$G$8 -> 0
B11: Avrg Days / Week | C11: 6 | F11: 0.075 | G11: =G10+(G10*F11) -> 0 | H11: =G11-$G$8 -> 0
B12: Avrg Hours / Month | C12: =C10*C8 -> 210 | F12: 0.1 | G12: =G11+(G11*F12) -> 0 | H12: =G12-$G$8 -> 0
B14: STAFF | G14: Hourly Rate + 2.5% | H14: Hourly Rate + 5% | I14: Hourly Rate + 7.5% | J14: Hourly Rate + 10%
C15: Unit | D15: REQ | E15: Cost ex GST | F15: Total ex GST
B16: TRADESMAN_LEADING HAND | C16: HR | D16: 1 | E16: 94 | F16: =D16*E16 -> 94 | G16: =E16+(F16*$F$9) -> 96.35 | H16: =E16+(E16*$F$10) -> 98.7 | I16: =E16+(E16*$F$11) -> 101.05 | J16: =E16+(E16*$F$12) -> 103.4
C17: DAY | D17: 1 | E17: =E16*$C$10 -> 822.5 | F17: =D17*E17 -> 822.5 | G17: =G16*$C$10 -> 843.0625 | H17: =H16*$C$10 -> 863.625 | I17: =I16*$C$10 -> 884.1875 | J17: =J16*$C$10 -> 904.75
B18: =B16 -> TRADESMAN_LEADING HAND | C18: WEEK | D18: 1 | E18: =E17*$C$11 -> 4935 | F18: =D18*E18 -> 4935 | G18: =G17*$C$11 -> 5058.375 | H18: =H17*$C$11 -> 5181.75 | I18: =I17*$C$11 -> 5305.125 | J18: =J17*$C$11 -> 5428.5
C19: MONTH | D19: 1 | E19: =E17*$C$8 -> 19740 | F19: =D19*E19 -> 19740 | G19: =G17*$C$8 -> 20233.5 | H19: =H17*$C$8 -> 20727 | I19: =I17*$C$8 -> 21220.5 | J19: =J17*$C$8 -> 21714
B21: QTY Staff in Crew | C21: =COUNTA(B18,B19,B20) -> 1
B23: Crew #1 | C23: HR | D23: 1 | E23: =E44*2+E51 -> 254 | F23: =D23*E23 -> 254 | G23: =E23+(F23*$F$9) -> 260.35 | H23: =E23+(E23*$F$10) -> 266.7 | I23: =E23+(E23*$F$11) -> 273.05 | J23: =E23+(E23*$F$12) -> 279.4
C24: DAY | D24: 1 | E24: =E23*$C$10 -> 2222.5 | F24: =D24*E24 -> 2222.5 | G24: =G23*$C$10 -> 2278.0625 | H24: =H23*$C$10 -> 2333.625 | I24: =I23*$C$10 -> 2389.1875 | J24: =J23*$C$10 -> 2444.75
B25: =B44 -> TRADESMAN_PLUMBER_OPERATOR | C25: WEEK | D25: 1 | E25: =E24*$C$11 -> 13335 | F25: =D25*E25 -> 13335 | G25: =G24*$C$11 -> 13668.375 | H25: =H24*$C$11 -> 14001.75 | I25: =I24*$C$11 -> 14335.125 | J25: =J24*$C$11 -> 14668.5
B26: =B44 -> TRADESMAN_PLUMBER_OPERATOR | C26: MONTH | D26: 1 | E26: =E24*$C$8 -> 53340 | F26: =D26*E26 -> 53340 | G26: =G24*$C$8 -> 54673.5 | H26: =H24*$C$8 -> 56007 | I26: =I24*$C$8 -> 57340.5 | J26: =J24*$C$8 -> 58674
B27: =B51 -> T/A & Apprentice
B28: QTY Staff in Crew | C28: =COUNTA(B25,B26,B27) -> 3
B30: Crew #2 | C30: HR | D30: 1 | E30: =E44*2+E51 -> 254 | F30: =D30*E30 -> 254 | G30: =E30+(F30*$F$9) -> 260.35 | H30: =E30+(E30*$F$10) -> 266.7 | I30: =E30+(E30*$F$11) -> 273.05 | J30: =E30+(E30*$F$12) -> 279.4
C31: DAY | D31: 1 | E31: =E30*$C$10 -> 2222.5 | F31: =D31*E31 -> 2222.5 | G31: =G30*$C$10 -> 2278.0625 | H31: =H30*$C$10 -> 2333.625 | I31: =I30*$C$10 -> 2389.1875 | J31: =J30*$C$10 -> 2444.75
B32: =B44 -> TRADESMAN_PLUMBER_OPERATOR | C32: WEEK | D32: 1 | E32: =E31*$C$11 -> 13335 | F32: =D32*E32 -> 13335 | G32: =G31*$C$11 -> 13668.375 | H32: =H31*$C$11 -> 14001.75 | I32: =I31*$C$11 -> 14335.125 | J32: =J31*$C$11 -> 14668.5
B33: =B44 -> TRADESMAN_PLUMBER_OPERATOR | C33: MONTH | D33: 1 | E33: =E31*$C$8 -> 53340 | F33: =D33*E33 -> 53340 | G33: =G31*$C$8 -> 54673.5 | H33: =H31*$C$8 -> 56007 | I33: =I31*$C$8 -> 57340.5 | J33: =J31*$C$8 -> 58674
B34: =B51 -> T/A & Apprentice
B35: QTY Staff in Crew | C35: =COUNTA(B32,B33,B34) -> 3
B37: Crew #3 | C37: HR | D37: 1 | E37: =E44*2+E51 -> 254 | F37: =D37*E37 -> 254 | G37: =E37+(F37*$F$9) -> 260.35 | H37: =E37+(E37*$F$10) -> 266.7 | I37: =E37+(E37*$F$11) -> 273.05 | J37: =E37+(E37*$F$12) -> 279.4
C38: DAY | D38: 1 | E38: =E37*$C$10 -> 2222.5 | F38: =D38*E38 -> 2222.5 | G38: =G37*$C$10 -> 2278.0625 | H38: =H37*$C$10 -> 2333.625 | I38: =I37*$C$10 -> 2389.1875 | J38: =J37*$C$10 -> 2444.75
B39: =B44 -> TRADESMAN_PLUMBER_OPERATOR | C39: WEEK | D39: 1 | E39: =E38*$C$11 -> 13335 | F39: =D39*E39 -> 13335 | G39: =G38*$C$11 -> 13668.375 | H39: =H38*$C$11 -> 14001.75 | I39: =I38*$C$11 -> 14335.125 | J39: =J38*$C$11 -> 14668.5
B40: =B44 -> TRADESMAN_PLUMBER_OPERATOR | C40: MONTH | D40: 1 | E40: =E38*$C$8 -> 53340 | F40: =D40*E40 -> 53340 | G40: =G38*$C$8 -> 54673.5 | H40: =H38*$C$8 -> 56007 | I40: =I38*$C$8 -> 57340.5 | J40: =J38*$C$8 -> 58674
B41: =B51 -> T/A & Apprentice
B42: QTY Staff in Crew | C42: =COUNTA(B39,B40,B41) -> 3
B44: TRADESMAN_PLUMBER_OPERATOR | C44: HR | D44: 1 | E44: 92 | F44: =D44*E44 -> 92 | G44: =E44+(F44*$F$9) -> 94.3 | H44: =E44+(E44*$F$10) -> 96.6 | I44: =E44+(E44*$F$11) -> 98.9 | J44: =E44+(E44*$F$12) -> 101.2
C45: DAY | D45: 1 | E45: =E44*$C$10 -> 805 | F45: =D45*E45 -> 805 | G45: =G44*$C$10 -> 825.125 | H45: =H44*$C$10 -> 845.25 | I45: =I44*$C$10 -> 865.375 | J45: =J44*$C$10 -> 885.5
B46: =B44 -> TRADESMAN_PLUMBER_OPERATOR | C46: WEEK | D46: 1 | E46: =E45*$C$11 -> 4830 | F46: =D46*E46 -> 4830 | G46: =G45*$C$11 -> 4950.75 | H46: =H45*$C$11 -> 5071.5 | I46: =I45*$C$11 -> 5192.25 | J46: =J45*$C$11 -> 5313
C47: MONTH | D47: 1 | E47: =E45*$C$8 -> 19320 | F47: =D47*E47 -> 19320 | G47: =G45*$C$8 -> 19803 | H47: =H45*$C$8 -> 20286 | I47: =I45*$C$8 -> 20769 | J47: =J45*$C$8 -> 21252
B49: QTY Staff in Crew | C49: =COUNTA(B46,B47,B48) -> 1
B51: T/A & Apprentice | C51: HR | D51: 1 | E51: 70 | F51: =D51*E51 -> 70 | G51: =E51+(F51*$F$9) -> 71.75 | H51: =E51+(E51*$F$10) -> 73.5 | I51: =E51+(E51*$F$11) -> 75.25 | J51: =E51+(E51*$F$12) -> 77
C52: DAY | D52: 1 | E52: =E51*$C$10 -> 612.5 | F52: =D52*E52 -> 612.5 | G52: =G51*$C$10 -> 627.8125 | H52: =H51*$C$10 -> 643.125 | I52: =I51*$C$10 -> 658.4375 | J52: =J51*$C$10 -> 673.75
B53: =B51 -> T/A & Apprentice | C53: WEEK | D53: 1 | E53: =E52*$C$11 -> 3675 | F53: =D53*E53 -> 3675 | G53: =G52*$C$11 -> 3766.875 | H53: =H52*$C$11 -> 3858.75 | I53: =I52*$C$11 -> 3950.625 | J53: =J52*$C$11 -> 4042.5
C54: MONTH | D54: 1 | E54: =E52*$C$8 -> 14700 | F54: =D54*E54 -> 14700 | G54: =G52*$C$8 -> 15067.5 | H54: =H52*$C$8 -> 15435 | I54: =I52*$C$8 -> 15802.5 | J54: =J52*$C$8 -> 16170
B56: QTY Staff in Crew | C56: =COUNTA(B53,B54,B55) -> 1

Sheet Equip&HIRE
D2: TCS PROJECT USE | G2: CAT Rental (ROK) | J2: COATES (ROK) | M2: ONSITE
A3: DESCRIPTION | B3: QTY | D3: WEEKLY (5 day) | E3: COMMENTS | G3: WEEKLY (5 day) | H3: COMMENTS | J3: WEEKLY (5 day) | K3: COMMENTS | M3: DAILY | N3: WEEKLY (5 day) | O3: COMMENTS
A4: Skid Steer Loader_Tracked | B4: 0 | D4: 0 | G4: 0 | J4: 0 | M4: 0 | N4: 262
A5: Skid Steer Loader_Wheeled | B5: 0 | D5: 300 | E5: =B5*D5 -> 0 | G5: 250 | J5: 192 | M5: 0 | N5: 0
A7: 4.5-6Ton_Excavator | B7: 0 | D7: 200 | G7: 0 | J7: 0 | M7: 0 | N7: 0
A8: 8Ton_Excavator | B8: 0 | D8: 250 | E8: =B8*D8 -> 0 | G8: 0 | J8: 0 | M8: 0 | N8: 0
A9: 10-12Ton_Excavator | B9: 0 | D9: 310 | E9: =B9*D9 -> 0 | G9: 310 | H9: 13T | J9: 301 | K9: 12T | M9: 0 | N9: 300 | O9: 13T
A10: 14-16Ton_Excavator | B10: 0 | D10: 440 | E10: =B10*D10 -> 0 | G10: 370 | H10: 17T | J10: 375 | K10: 14T | M10: 0 | N10: 295 | O10: 14T
A11: 20-24Ton_Excavator | B11: 0 | D11: 450 | E11: =B11*D11 -> 0 | G11: 480 | H11: 25T | J11: 417 | K11: 20T | M11: 0 | N11: 444 | O11: 20T
A13: Ripper_10-12T | B13: 0 | D13: 26 | G13: 0 | J13: 25.7 | M13: 0 | N13: 0
A14: Ripper_14-16T | B14: 0 | D14: 26 | G14: 0 | J14: 25.7 | M14: 0 | N14: 21
A15: Ripper_20-24T | B15: 0 | D15: 30 | G15: 0 | J15: 30.1 | M15: 0 | N15: 23
A16: Breaker_10-12T | B16: 0 | D16: 0 | G16: 0 | J16: 0 | M16: 0 | N16: 0
A17: Auger Drive_10-12T | B17: 0 | D17: 115 | E17: =B17*D17 -> 0 | G17: 0 | J17: 0 | M17: 0 | N17: 0
A18: 300Dia Auger Drill | B18: 0 | D18: 50 | G18: 0 | J18: 0 | M18: 0 | N18: 0
A20: 2-4T_Tipper Truck | B20: 0 | D20: 180 | E20: =B20*D20 -> 0 | G20: 0 | J20: 180 | K20: 2-3T | M20: 0 | N20: 130 | O20: 2-3T
A21: 6-12T_Tipper Truck | B21: 0 | D21: 400 | E21: =B21*D21 -> 0 | G21: 0 | J21: 238 | K21: 6T | M21: 0 | N21: 0
A23: <10T_Articulated Site Tipper | B23: 0 | D23: 341 | E23: =B23*D23 -> 0 | G23: 0 | J23: 243 | K23: 9T | M23: 0 | N23: 0
A24: Upright Rammer_Wacker | B24: 0 | D24: 50 | E24: =B24*D24 -> 0 | G24: 0 | J24: 48 | M24: 0 | N24: 46
A25: Trench Roller_Dbl Drum_Remote | B25: 0 | D25: 180 | E25: =B25*D25 -> 0 | G25: 0 | J25: 121 | M25: 0 | N25: 98 | O25: Rller - padfot?
A26: <26Ft_Scissor Lift - Diesel | B26: 0 | D26: 150 | E26: =B26*D26 -> 0 | G26: 0 | J26: 89 | M26: 0 | N26: 112
A27: <26Ft_Scissor Lift - Elec | B27: 0 | D27: 0 | E27: =B27*D27 -> 0 | G27: 0 | J27: 0 | M27: 0 | N27: 0
A28: <34Ft_Boom Lift - Diesel | B28: 0 | D28: 150 | E28: =B28*D28 -> 0 | G28: 0 | J28: 96 | M28: 0 | N28: 140
A29: <34Ft_Boom Lift - Elec | B29: 0 | D29: 0 | E29: =B29*D29 -> 0 | G29: 0 | J29: 0 | M29: 0 | N29: 0
A31: Porta Loo_No Tank | B31: 0 | D31: 5 | E31: =B31*D31 -> 0 | G31: 0 | J31: 5 | M31: 0 | N31: 7.5
A32: 3.6*3m Demantable Office | B32: 0 | D32: 0 | E32: =B32*D32 -> 0 | G32: 0 | J32: 15 | K32: 42D Min. | M32: 0 | N32: 13
A33: 20Ft Shipping Container | B33: 0 | D33: 5 | E33: =B33*D33 -> 0 | G33: 0 | J33: 4 | K33: 42D Min. | M33: 0 | N33: 0
A34: Quick Cut Demo Saw | B34: 0 | D34: 0 | E34: =B34*D34 -> 0 | G34: 0 | J34: 100 | M34: 0 | N34: 50
A35: Sngl Ph_6KVA Genset | B35: 0 | D35: 50 | E35: =B35*D35 -> 0 | G35: 0 | J35: 45 | M35: 0 | N35: 35
A36: Diesel Air Compressor_Trailer | B36: 0 | D36: 0 | E36: =B36*D36 -> 0 | G36: 0 | J36: 73 | M36: 0 | N36: 68
A37: Air Breaker - Heavy | B37: 0 | D37: 0 | E37: =B37*D37 -> 0 | G37: 0 | J37: 34 | M37: 0 | N37: 0
A38: Air Hose <10m | B38: 0 | D38: 0 | E38: =B38*D38 -> 0 | G38: 0 | J38: 9 | M38: 0 | N38: 1.2
A39: Elec Breaker/Jachammer | B39: 0 | D39: 0 | E39: =B39*D39 -> 0 | G39: 0 | J39: 45 | M39: 0 | N39: 0
A40: Flexdrive Motor Unit | B40: 0 | D40: 0 | E40: =B40*D40 -> 0 | G40: 0 | J40: 25 | M40: 0 | N40: 27
A41: Flexdrive_Pump Shaft | B41: 0 | D41: 0 | E41: =B41*D41 -> 0 | G41: 0 | J41: 30 | M41: 0 | N41: 22
A42: Temporary Power Board | B42: 0 | D42: 25 | E42: =B42*D42 -> 0 | G42: 0 | J42: 30 | M42: 0 | N42: 17
A44: Dual CabUte | B44: 0 | D44: 125 | E44: =B44*D44 -> 0 | G44: 0 | J44: 0 | M44: 0 | N44: 0
A45: 10m3_Skip Bin | B45: 0 | D45: 40 | E45: =B45*D45 -> 0 | G45: 0 | J45: 0 | M45: 0 | N45: 0
A46: Vac Truck / HR | B46: 0 | D46: 200 | E46: =B46*D46 -> 0 | G46: 0 | J46: 0 | M46: 0 | N46: 0
B47: 0 | D47: 0 | G47: 0 | J47: 0 | M47: 0 | N47: 0
B48: 0 | D48: 0 | G48: 0 | J48: 0 | M48: 0 | N48: 0
A50: TRANSPORT_Ex BRIS - Return | B50: 0 | D50: 0 | G50: 0 | J50: 0 | M50: 0 | N50: 0
A51: TRANSPORT_Ex ROK - Return | B51: 0 | D51: 0 | G51: 0 | J51: 480 | K51: 22T | M51: 0 | N51: 0 | O51: 0

Sheet Civil Rate  BOQ 
A6: Adress | I6: Contract
A7: ROADWORKS AND CIVIL SERVICES
A9: BILL OF QUANTITIES | I9: Date
C11: SUMMARY
A14: 1 | C14: TOTAL PART A - PRELIMS, SITE ESTABLISHMENT, E&S Controls & PREPARATIONS | L14: =O79 -> 0
A15: 2 | C15: TOTAL PART B - EARTHWORKS | L15: =O218 -> 0
A16: 3 | C16: TOTAL PART C - ROADWORKS | L16: =O322 -> 0
A17: 4 | C17: TOTAL PART D - STORMWATER DRAINAGE | L17: =O463 -> 25129.865
A18: 5 | C18: TOTAL PART E - POTABLE WATER RETICULATION | L18: =O550 -> 0
A19: 6 | C19: TOTAL PART F - SEWERAGE RETICULATION (RIGS) | L19: =O679 -> 0
A20: 7 | C20: TOTAL PART G - STORMWATER TREATMENT | L20: =O829 -> 0
A21: 8 | C21: TOTAL PART H - ELECTRICAL & COMMUNICATIONS | L21: =O869 -> 0
A22: 9 | C22: TOTAL PART I - INTERNAL PLUMBING | L22: =O950 -> 0
A24: 9 | C24: SUB-TOTAL: | L24: =SUM(L14:M23) -> 25129.865
A25: 14 | C25: COMBINED QLEAVE LEVY AND WORKPLACE HEALTH AND SAFETY FEE | L25: (By Principal) | Q25: =L24/6 -> 4188.3109
A27: ITEM DESCRIPTION | H27: QTY UNIT | L27: Rate | O27: Amount
A30: PART A - SITE ESTABLISHMENT AND PREPARATION
A32: 1. Site establishment including mobilisation of plant and personnel. | J32: Item | L32: 6081.91 | O32: =H32*L32 -> 0
A33: 1. Site DeMob & Clean | J33: Item | L33: 3100 | O33: =H33*L33 -> 0
A35: 2. Supply and erect approved 1200mm x 900mm project Notice | J35: Item | L35: 364.91 | O35: =H35*L35 -> 0
A36: board to Local Authority requirements.
A38: 3. Provision for traffic, including installation of temporary warning | J38: Item | L38: 1450 | O38: =H38*L38 -> 0
A39: devices and/or traffic controllers and /or traffic controllers and
A40: maintenance of access for site traffic, in accordance with approved
A41: Traffic Management Plan (to be organised by contractor)
A43: 4. Allowance for service location and potholing as required to | J43: Item | L43: 1715.1 | O43: =H43*L43 -> 0
A44: confirm existing services and protect infrastructure throughout
A45: construction.
A47: 5. Supply all materials, construct, maintain and remove on | J47: Item | L47: 5850 | O47: =H47*L47 -> 0
A48: completion of works the erosion and sediment control measures as
A49: detailed. Note that the Contractor must engage their own CPESC for
A50: ongoing management of ESC Control measures on site.
A52: 6.Clearing and grubbing, including removal of trees and grasses, | J52: Item | L52: 650 | O52: =H52*L52 -> 0
A53: existing fences, rubbish and debris from all work areas, including
A54: mulching of trees & vegetation or removal from site as directed.
A56: 7. Provision of Level 4 Arborist for attendance at pre-start meeting | J56: Item | L56: 6252.2
A57: and during cleaning operations.
A59: 8. Implementation of approved Vegetation Management Plan | J59: Item | L59: 4378.97 | O59: =H59*L59 -> 0
A60: procedures, including supply and establishent of temporary fencing
A61: for protection of identified trees, vegetation to be preserved &
A62: management of mulch stockpiles.
A64: 9. Provision for obtaining EPA resuce permit and for payment to | J64: Item | O64: By Client
A65: accredited wildlife spotter / catched for attendance during clearing
A66: and grubbing operations, in accordance with approved Fauna
A67: Management Plan requirements.
A69: 10.Condition of adjacent buildings and structures, carried out by | J69: Item | L69: 2432.76 | O69: =H69*L69 -> 0
A70: accredited personnel prior to construction. - DELAP REPORT
A72: SURVEY | J72: Item | L72: 11200 | O72: =H72*L72 -> 0
A73: Construciton Management Plan | J73: Item | L73: 1020 | O73: =H73*L73 -> 0
A74: Geotech Report | J74: Item | L74: 1888 | O74: =H74*L74 -> 0
A75: Skip Bin & Rubbish | J75: Item | L75: 650 | O75: =H75*L75 -> 0
A79: TOTAL PART A: | O79: =SUM(O30:P78) -> 0
A80: (Carried forward to Summary)
A82: PART B - EARTHWORKS
A84: 1. Strip, stockpile and replace topsoil to allotments, verge and
A85: verge and batters including final trim and soil amendment (100mm
A86: nominal depth).
A88: (a) Strip to stockpiles. | J88: cu.m.
A89: (d) Respread topsoil from stockpiles | J89: cu.m.
A90: (c) Removal of excess topsoil offsite. | J90: cu.m.
A93: 3. Earthworks in all materials including compaction, trimming and
A94: testing (by RPEQ Geotechnical Engineer) as specified:
A96: (a) On leads from site excavations to structural filling. (Nett cut) | J96: cu.m. | L96: 14.52 | O96: =H96*L96 -> 0
A98: (b) Import of acceptable fill material to site (to LCC Requirements) | J98: cu.m. | L98: 22.56 | O98: =H98*L98 -> 0
A99: inclusive of compaction factor (compacted fill in place).
A101: (c) Trench Spoil (including stormwater, sewer, water & | J101: cu.m. | L101: 13.74 | O101: =H101*L101 -> 0
A102: electrical) to structural fill (Provisional)
A104: (d) Excavation of unsuitable material below ground surface or | H104: 0 | J104: cu.m. | L104: 33.92 | O104: =H104*L104 -> 0
A105: road subgrade , including removal to nonstructural areas and
A106: replacement with compacted,approved site material. (Provisional)
A109: Strip Topsoil | J109: cu.m. | L109: 9.6 | O109: =H109*L109 -> 0
A110: Remove Topsoil | J110: cu.m. | L110: 6 | O110: =H110*L110 -> 0
A111: Cut-Fill | J111: cu.m. | L111: 15.8 | O111: =H111*L111 -> 0
A112: Remove Trees_onsite | J112: Item | L112: 600 | O112: =H112*L112 -> 0
A113: Remove Spoil From site | J113: cu.m. | L113: 31 | O113: =H113*L113 -> 0
A115: 4 Extra/over Item 3 for excavation of general earthworks in rock by | J115: cu.m. | L115: 25 | O115: =H115*L115 -> 0
A116: excavator larger than 148kW (Provisional).
A119: 5. Level 1 testing carried out by a NATA-accredited | J119: Lump Sum | L119: 3100 | O119: =H119*L119 -> 0
A120: testing authority, including certification by an approved
A121: geotechnical engineer and Registered Professional
A122: Engineer Queensland (RPEQ), carried out in
A123: accordance with AS3798, including relative
A124: compaction testing carried out in accordance with
A125: AS1289 Series 5.
A127: 6. Global stability analysis and certification, carried out on the | J127: Item | L127: 3649.14 | O127: =H127*L127 -> 0
A128: completed earthworks and retaining walls by the Contractor's
A129: geotechnical engineer and Registered Professional Engineer
A130: Queensland (RPEQ).
A133: 7. Allowance for site inspections by Principal's geotechnical | J133: PC Item
A134: consultant, only if ordered by Superintendent. (Provisional)
A137: 8. Grass seeding to the following areas: | J137: ha | L137: 1946.21 | O137: =H137*L137 -> 0
A138: (a) Allotments
A139: (b) Extra/over - Supply and apply Vital Chemical spray or | J139: ha | L139: 5589.01 | O139: =H139*L139 -> 0
A140: equivalent approved product (Provisional)
A143: 9. Provide detailed design, supply all materials and construct the
A144: following precast concrete sleeper retaining wall system complete,
A145: including all components, additional excavation as required,
A146: drainage layer, connection of aggregate drains to stormwater system,
A147: approved backfilling, temporary safety fencing during construction,
A148: provision of structural design and supervision certificate by
...
